<?xml version="1.0" encoding="UTF-8"?>
<profile generated="2014-07-21T06:12:38Z" xmlns="http://feed.elasticstats.com/schema/soccer/sr/v2/players-profile.xsd">
  <player id="01b78da8-4c54-4b74-8da3-16afcc3d99ad" country_code="COL" preferred_foot="R" height_in="69" weight_lb="0" height_cm="175" weight_kg="0" first_name="Santiago" last_name="Arias" country="Colombia">
    <teams>
      <team id="42fafe63-cc2f-40c2-a196-b5cc6dbdfa87" name="Colombia" country_code="COL" position="D" is_manager="false" is_player="true" country="Colombia" jersey_number="4"/>
    </teams>
    <statistics>
      <season year="2014">
        <statistic goals="-1" goal_frequency="0" goal_average="0.0" goal_assists="-1" matches_played="3" matches_started="0" minutes_played="124" yellow_cards="-1" yellow_red_cards="-1" red_cards="-1" substitutions_out="-1" substitutions_in="2">
          <category id="ccb3c550-8bdb-435f-9f4e-8c125f7298b9" name="International" country_code="XZ" country="International"/>
          <tournament_group id="ea97fe54-4712-4bd7-b643-8409887f9f61" name="World Championship"/>
          <team id="42fafe63-cc2f-40c2-a196-b5cc6dbdfa87" name="Colombia" alias="COL" country_code="COL" country="Colombia" type="team"/>
        </statistic>
      </season>
      <season year="2013">
        <statistic goals="-1" goal_frequency="0" goal_average="0.0" goal_assists="-1" matches_played="-1" matches_started="0" minutes_played="0" yellow_cards="-1" yellow_red_cards="-1" red_cards="-1" substitutions_out="-1" substitutions_in="-1">
          <category id="77796062-f516-4e20-bc29-4fb6fba605b3" name="Netherlands" country_code="NLD" country="Netherlands"/>
          <tournament_group id="cd00e95a-f750-4053-9eab-04b3b1278ca7" name="KNVB beker"/>
          <tournament id="4777a2ca-fea5-428e-9f43-e2c6b06be0d1" name="KNVB beker"/>
          <team id="b55b5c50-5e49-4a6e-9fdc-1629e2f141a9" name="PSV Eindhoven" alias="PSV" country_code="NLD" country="Netherlands" type="team"/>
        </statistic>
        <statistic goals="1" goal_frequency="0" goal_average="0.0" goal_assists="1" matches_played="25" matches_started="0" minutes_played="2177" yellow_cards="5" yellow_red_cards="-1" red_cards="-1" substitutions_out="2" substitutions_in="-1">
          <category id="77796062-f516-4e20-bc29-4fb6fba605b3" name="Netherlands" country_code="NLD" country="Netherlands"/>
          <tournament_group id="c064795b-be1e-45f8-9727-28c7e00cbaef" name="Eredivisie"/>
          <team id="b55b5c50-5e49-4a6e-9fdc-1629e2f141a9" name="PSV Eindhoven" alias="PSV" country_code="NLD" country="Netherlands" type="team"/>
        </statistic>
        <statistic goals="-1" goal_frequency="0" goal_average="0.0" goal_assists="-1" matches_played="-1" matches_started="0" minutes_played="0" yellow_cards="-1" yellow_red_cards="-1" red_cards="-1" substitutions_out="-1" substitutions_in="-1">
          <category id="c4ef0886-dfee-4725-81eb-1bb919be832a" name="International Clubs" country_code="XZ" country="International"/>
          <tournament_group id="7a480297-4942-4426-ba1d-a37284fe4dc2" name="UEFA Champions League"/>
          <team id="b55b5c50-5e49-4a6e-9fdc-1629e2f141a9" name="PSV Eindhoven" alias="PSV" country_code="NLD" country="Netherlands" type="team"/>
        </statistic>
        <statistic goals="-1" goal_frequency="0" goal_average="0.0" goal_assists="-1" matches_played="2" matches_started="0" minutes_played="180" yellow_cards="1" yellow_red_cards="-1" red_cards="-1" substitutions_out="-1" substitutions_in="-1">
          <category id="77796062-f516-4e20-bc29-4fb6fba605b3" name="Netherlands" country_code="NLD" country="Netherlands"/>
          <tournament_group id="ff14a3ef-bfd8-4e48-a24c-369c89fb0f31" name="Eerste Divisie"/>
          <tournament id="18493e74-b61e-4964-88c1-0fd035b3829a" name="Eerste Divisie"/>
          <team id="0083fa4c-b5c6-44a1-a917-b0fda08135f3" name="Jong PSV Eindhoven" alias="" country_code="NLD" country="Netherlands" type="team"/>
        </statistic>
        <statistic goals="-1" goal_frequency="0" goal_average="0.0" goal_assists="-1" matches_played="6" matches_started="0" minutes_played="540" yellow_cards="1" yellow_red_cards="-1" red_cards="-1" substitutions_out="-1" substitutions_in="-1">
          <category id="c4ef0886-dfee-4725-81eb-1bb919be832a" name="International Clubs" country_code="XZ" country="International"/>
          <tournament_group id="54cf60c3-93f3-4f28-8579-5513deb26b5f" name="UEFA Europa League"/>
          <team id="b55b5c50-5e49-4a6e-9fdc-1629e2f141a9" name="PSV Eindhoven" alias="PSV" country_code="NLD" country="Netherlands" type="team"/>
        </statistic>
      </season>
    </statistics>
    <!-- 158583/1405922788 -->
  </player>
</profile>
