<?xml version="1.0" encoding="UTF-8"?>
<profile generated="2014-07-21T06:17:37Z" xmlns="http://feed.elasticstats.com/schema/soccer/sr/v2/players-profile.xsd">
  <player id="7ee6fc04-1308-4a66-8f1c-febc754a7a5b" country_code="CIV" preferred_foot="R" height_in="74" weight_lb="200" height_cm="187" weight_kg="90" first_name="Didier" last_name="Drogba" country="C么te D'Ivoire">
    <teams>
      <team id="0bca6ba8-1ff0-411c-90e6-203b0d38ab96" name="Ivory Coast" country_code="CIV" position="F" is_manager="false" is_player="true" country="C么te D'Ivoire" jersey_number="11"/>
    </teams>
    <statistics>
      <season year="2014">
        <statistic goals="-1" goal_frequency="0" goal_average="0.0" goal_assists="-1" matches_played="3" matches_started="0" minutes_played="136" yellow_cards="1" yellow_red_cards="-1" red_cards="-1" substitutions_out="1" substitutions_in="2">
          <category id="ccb3c550-8bdb-435f-9f4e-8c125f7298b9" name="International" country_code="XZ" country="International"/>
          <tournament_group id="ea97fe54-4712-4bd7-b643-8409887f9f61" name="World Championship"/>
          <team id="0bca6ba8-1ff0-411c-90e6-203b0d38ab96" name="Ivory Coast" alias="CIV" country_code="CIV" country="C么te D'Ivoire" type="team"/>
        </statistic>
        <statistic goals="1" goal_frequency="0" goal_average="0.0" goal_assists="-1" matches_played="1" matches_started="0" minutes_played="90" yellow_cards="-1" yellow_red_cards="-1" red_cards="-1" substitutions_out="-1" substitutions_in="-1">
          <category id="ccb3c550-8bdb-435f-9f4e-8c125f7298b9" name="International" country_code="XZ" country="International"/>
          <tournament_group id="2b2c2a26-29f3-403f-beba-854f76fc979b" name="WC Qualification"/>
          <team id="0bca6ba8-1ff0-411c-90e6-203b0d38ab96" name="Ivory Coast" alias="CIV" country_code="CIV" country="C么te D'Ivoire" type="team"/>
        </statistic>
      </season>
      <season year="2013">
        <statistic goals="2" goal_frequency="0" goal_average="0.0" goal_assists="3" matches_played="8" matches_started="0" minutes_played="662" yellow_cards="1" yellow_red_cards="-1" red_cards="-1" substitutions_out="3" substitutions_in="-1">
          <category id="c4ef0886-dfee-4725-81eb-1bb919be832a" name="International Clubs" country_code="XZ" country="International"/>
          <tournament_group id="7a480297-4942-4426-ba1d-a37284fe4dc2" name="UEFA Champions League"/>
          <team id="11940ded-4f34-49ee-a8dd-ea9402fb34df" name="Galatasaray Istanbul" alias="GAL" country_code="TUR" country="Turkey" type="team"/>
        </statistic>
        <statistic goals="10" goal_frequency="0" goal_average="0.0" goal_assists="3" matches_played="24" matches_started="0" minutes_played="1972" yellow_cards="4" yellow_red_cards="-1" red_cards="-1" substitutions_out="6" substitutions_in="1">
          <category id="9637e80b-096a-45bf-b4fa-59da8d456467" name="Turkey" country_code="TUR" country="Turkey"/>
          <tournament_group id="fa9452f9-2b46-4975-8078-949418776dc9" name="Super Lig"/>
          <tournament id="076c36b5-1ebd-48c3-a14b-c3e26c4198c8" name="Super Lig"/>
          <team id="11940ded-4f34-49ee-a8dd-ea9402fb34df" name="Galatasaray Istanbul" alias="GAL" country_code="TUR" country="Turkey" type="team"/>
        </statistic>
        <statistic goals="1" goal_frequency="0" goal_average="0.0" goal_assists="-1" matches_played="3" matches_started="0" minutes_played="210" yellow_cards="-1" yellow_red_cards="-1" red_cards="-1" substitutions_out="2" substitutions_in="-1">
          <category id="9637e80b-096a-45bf-b4fa-59da8d456467" name="Turkey" country_code="TUR" country="Turkey"/>
          <tournament_group id="cc4b58e2-9d0d-4a0b-a189-0f10d4e4f0ff" name="Turkiye Kupasi"/>
          <team id="11940ded-4f34-49ee-a8dd-ea9402fb34df" name="Galatasaray Istanbul" alias="GAL" country_code="TUR" country="Turkey" type="team"/>
        </statistic>
      </season>
    </statistics>
    <!-- 1222/1405922880 -->
  </player>
</profile>
