<?xml version="1.0" encoding="UTF-8"?>
<profile generated="2014-07-21T14:11:37Z" xmlns="http://feed.elasticstats.com/schema/soccer/sr/v2/players-profile.xsd">
  <player id="fcaadf35-34f3-416c-ba70-1a413a72d0d2" country_code="GRC" preferred_foot="R" height_in="72" weight_lb="167" height_cm="182" weight_kg="75" first_name="Loukas" last_name="Vyntra" country="Greece">
    <teams>
      <team id="56915cf9-6045-49c9-aba1-4e7691f23cce" name="Greece" country_code="GRC" position="D" is_manager="false" is_player="true" country="Greece" jersey_number="11"/>
    </teams>
    <statistics>
      <season year="2014">
        <statistic goals="-1" goal_frequency="0" goal_average="0.0" goal_assists="-1" matches_played="-1" matches_started="0" minutes_played="0" yellow_cards="-1" yellow_red_cards="-1" red_cards="-1" substitutions_out="-1" substitutions_in="-1">
          <category id="ccb3c550-8bdb-435f-9f4e-8c125f7298b9" name="International" country_code="XZ" country="International"/>
          <tournament_group id="ea97fe54-4712-4bd7-b643-8409887f9f61" name="World Championship"/>
          <team id="56915cf9-6045-49c9-aba1-4e7691f23cce" name="Greece" alias="GRE" country_code="GRC" country="Greece" type="team"/>
        </statistic>
        <statistic goals="-1" goal_frequency="0" goal_average="0.0" goal_assists="-1" matches_played="2" matches_started="0" minutes_played="108" yellow_cards="-1" yellow_red_cards="-1" red_cards="-1" substitutions_out="-1" substitutions_in="1">
          <category id="ccb3c550-8bdb-435f-9f4e-8c125f7298b9" name="International" country_code="XZ" country="International"/>
          <tournament_group id="b09b64cc-6dc9-4504-862c-ba8f4e03aa98" name="WC Qualification"/>
          <team id="56915cf9-6045-49c9-aba1-4e7691f23cce" name="Greece" alias="GRE" country_code="GRC" country="Greece" type="team"/>
        </statistic>
      </season>
      <season year="2013">
        <statistic goals="-1" goal_frequency="0" goal_average="0.0" goal_assists="-1" matches_played="5" matches_started="0" minutes_played="450" yellow_cards="-1" yellow_red_cards="-1" red_cards="-1" substitutions_out="-1" substitutions_in="-1">
          <category id="eea96a14-a70c-410a-8950-5cdce820b68d" name="Spain" country_code="ESP" country="Spain"/>
          <tournament_group id="4ba865fd-363d-4df6-8afd-39ffacf0b0c7" name="Copa del Rey"/>
          <tournament id="948da02b-65e0-4ee2-bdeb-63fa9488b792" name="Copa del Rey"/>
          <team id="e0600eed-5501-4c5b-822d-5bd0b3fec115" name="Levante UD" alias="LEV" country_code="ESP" country="Spain" type="team"/>
        </statistic>
        <statistic goals="2" goal_frequency="0" goal_average="0.0" goal_assists="-1" matches_played="33" matches_started="0" minutes_played="2743" yellow_cards="7" yellow_red_cards="-1" red_cards="-1" substitutions_out="2" substitutions_in="2">
          <category id="eea96a14-a70c-410a-8950-5cdce820b68d" name="Spain" country_code="ESP" country="Spain"/>
          <tournament_group id="64e90d00-9ea0-4c91-8292-e78414439d54" name="Primera Division"/>
          <tournament id="004bb0f3-ea53-49e1-a699-5478c252466d" name="Primera Division"/>
          <team id="e0600eed-5501-4c5b-822d-5bd0b3fec115" name="Levante UD" alias="LEV" country_code="ESP" country="Spain" type="team"/>
        </statistic>
      </season>
    </statistics>
    <!-- 13436/1405951590 -->
  </player>
</profile>
