<?xml version="1.0" encoding="UTF-8"?>
<!-- Generation started @ 2014-05-14 16:31:17 +0000 -->
<player xmlns="http://feed.elasticstats.com/schema/basketball/profile-v2.0.xsd" id="b4fb962d-4f36-4b82-89e3-dec4733329c3" status="ACT" full_name="Dirk Nowitzki" first_name="Dirk" last_name="Nowitzki" abbr_name="D.Nowitzki" height="84" weight="245" position="F" primary_position="PF" jersey_number="41" experience="15" college="DJK Wurzburg" birth_place="Wurzburg,, DEU" birthdate="1978-06-19" updated="2013-07-23T15:01:07+00:00">
  <league id="4353138d-4c22-4396-95d8-5f587d2df25c" name="NBA" alias="NBA"/>
  <team id="583ecf50-fb46-11e1-82cb-f4ce4684ea4c" name="Mavericks" market="Dallas" alias="DAL"/>
  <draft team_id="583ecefd-fb46-11e1-82cb-f4ce4684ea4c" year="1998" round="1" pick="9"/>
  <seasons>
    <season id="5ddc217a-a958-4616-9bdf-e081022c440b" year="2013" type="REG">
      <team id="583ecf50-fb46-11e1-82cb-f4ce4684ea4c" name="Mavericks" market="Dallas" alias="DAL">
        <statistics>
          <total games_played="80" games_started="80" minutes="2628.0" field_goals_made="633" field_goals_att="1273" three_points_made="131" three_points_att="329" blocked_att="19" free_throws_made="338" free_throws_att="376" offensive_rebounds="40" defensive_rebounds="458" assists="216" turnovers="117" steals="73" blocks="45" personal_fouls="165" tech_fouls="7" points="1735" flagrant_fouls="0" free_throws_pct="0.899" two_points_pct="0.532" three_points_pct="0.398" field_goals_pct="0.497" rebounds="498" assists_turnover_ratio="1.85" two_points_made="502" two_points_att="944"/>
          <average points="21.7" blocked_att="0.24" turnovers="1.46" free_throws_att="4.7" field_goals_att="15.91" off_rebounds="0.5" two_points_att="11.8" assists="2.7" blocks="0.56" personal_fouls="2.06" two_points_made="6.28" flagrant_fouls="0.0" rebounds="6.23" three_points_made="1.64" minutes="32.9" def_rebounds="5.73" free_throws_made="4.23" field_goals_made="7.91" steals="0.91" three_points_att="4.11"/>
        </statistics>
      </team>
    </season>
  </seasons>
</player>
<!-- Generation ended @ 2014-05-14 16:31:17 +0000 -->
