<?xml version="1.0" encoding="UTF-8"?>
<!-- Generation started @ 2014-06-06 18:30:57 +0000 -->
<player xmlns="http://feed.elasticstats.com/schema/basketball/profile-v2.0.xsd" id="f0deff5f-c269-4389-9713-b8a7e70207cb" status="ACT" full_name="Marcin Gortat" first_name="Marcin" last_name="Gortat" abbr_name="M.Gortat" height="83" weight="240" position="C" primary_position="C" jersey_number="4" experience="6" college="RheinEnergie Cologne" birth_place="Lodz,, POL" birthdate="1984-02-17" updated="2013-10-30T23:13:41+00:00">
  <league id="4353138d-4c22-4396-95d8-5f587d2df25c" name="NBA" alias="NBA"/>
  <team id="583ec8d4-fb46-11e1-82cb-f4ce4684ea4c" name="Wizards" market="Washington" alias="WAS"/>
  <draft team_id="583ecfa8-fb46-11e1-82cb-f4ce4684ea4c" year="2005" round="2" pick="57"/>
  <seasons>
    <season id="5ddc217a-a958-4616-9bdf-e081022c440b" year="2013" type="REG">
      <team id="583ec8d4-fb46-11e1-82cb-f4ce4684ea4c" name="Wizards" market="Washington" alias="WAS">
        <statistics>
          <total games_played="81" games_started="80" minutes="2655.0" field_goals_made="455" field_goals_att="840" three_points_made="1" three_points_att="1" blocked_att="51" free_throws_made="157" free_throws_att="229" offensive_rebounds="202" defensive_rebounds="565" assists="138" turnovers="126" steals="41" blocks="121" personal_fouls="201" tech_fouls="3" points="1068" flagrant_fouls="0" free_throws_pct="0.686" two_points_pct="0.541" three_points_pct="1.0" field_goals_pct="0.542" rebounds="767" assists_turnover_ratio="1.1" two_points_made="454" two_points_att="839"/>
          <average points="13.2" blocked_att="0.63" turnovers="1.56" free_throws_att="2.83" field_goals_att="10.37" off_rebounds="2.49" two_points_att="10.36" assists="1.7" blocks="1.49" personal_fouls="2.48" two_points_made="5.6" flagrant_fouls="0.0" rebounds="9.47" three_points_made="0.01" minutes="32.8" def_rebounds="6.98" free_throws_made="1.94" field_goals_made="5.62" steals="0.51" three_points_att="0.01"/>
        </statistics>
      </team>
    </season>
  </seasons>
</player>
<!-- Generation ended @ 2014-06-06 18:30:57 +0000 -->
