<?xml version="1.0" encoding="UTF-8"?>
<!-- Generation started @ 2014-02-06 18:05:40 +0000 -->
<game xmlns="http://feed.elasticstats.com/schema/basketball/game-v2.0.xsd" id="7ec7ccea-3524-445b-b487-7aa738c3793a" status="closed" coverage="full" home_team="583ec773-fb46-11e1-82cb-f4ce4684ea4c" away_team="583ecae2-fb46-11e1-82cb-f4ce4684ea4c" scheduled="2014-02-06T00:00:00+00:00" duration="2:15" attendance="15205" lead_changes="2" times_tied="1" clock="00:00" quarter="4">
  <team name="Cavaliers" market="Cleveland" id="583ec773-fb46-11e1-82cb-f4ce4684ea4c" points="108">
    <scoring>
      <quarter number="1" sequence="1" points="17"/>
      <quarter number="2" sequence="2" points="32"/>
      <quarter number="3" sequence="3" points="31"/>
      <quarter number="4" sequence="4" points="28"/>
    </scoring>
    <leaders>
      <points>
        <player full_name="C.J. Miles" position="G" primary_position="SG" jersey_number="0" id="732b1bd6-d99a-4971-bc2c-4de4842b4a9a">
          <statistics minutes="29:23" field_goals_made="7" field_goals_att="15" field_goals_pct="46.7" three_points_made="4" three_points_att="11" three_points_pct="36.4" two_points_made="3" two_points_att="4" two_points_pct="0.75" blocked_att="0" free_throws_made="9" free_throws_att="10" free_throws_pct="90.0" offensive_rebounds="0" defensive_rebounds="3" rebounds="3" assists="3" turnovers="0" steals="0" blocks="0" assists_turnover_ratio="0" personal_fouls="2" tech_fouls="0" flagrant_fouls="0" pls_min="21" points="27"/>
        </player>
      </points>
      <rebounds>
        <player full_name="Anderson Varejao" position="C" primary_position="C" jersey_number="17" id="2c861696-d71b-4419-8a13-2f9e294ad0b5">
          <statistics minutes="34:32" field_goals_made="7" field_goals_att="16" field_goals_pct="43.8" three_points_made="0" three_points_att="0" three_points_pct="0.0" two_points_made="7" two_points_att="16" two_points_pct="0.438" blocked_att="0" free_throws_made="1" free_throws_att="1" free_throws_pct="100.0" offensive_rebounds="7" defensive_rebounds="6" rebounds="13" assists="5" turnovers="1" steals="2" blocks="0" assists_turnover_ratio="5.0" personal_fouls="4" tech_fouls="0" flagrant_fouls="0" pls_min="13" points="15"/>
        </player>
      </rebounds>
      <assists>
        <player full_name="Anderson Varejao" position="C" primary_position="C" jersey_number="17" id="2c861696-d71b-4419-8a13-2f9e294ad0b5">
          <statistics minutes="34:32" field_goals_made="7" field_goals_att="16" field_goals_pct="43.8" three_points_made="0" three_points_att="0" three_points_pct="0.0" two_points_made="7" two_points_att="16" two_points_pct="0.438" blocked_att="0" free_throws_made="1" free_throws_att="1" free_throws_pct="100.0" offensive_rebounds="7" defensive_rebounds="6" rebounds="13" assists="5" turnovers="1" steals="2" blocks="0" assists_turnover_ratio="5.0" personal_fouls="4" tech_fouls="0" flagrant_fouls="0" pls_min="13" points="15"/>
        </player>
      </assists>
    </leaders>
  </team>
  <team name="Lakers" market="Los Angeles" id="583ecae2-fb46-11e1-82cb-f4ce4684ea4c" points="119">
    <scoring>
      <quarter number="1" sequence="1" points="36"/>
      <quarter number="2" sequence="2" points="34"/>
      <quarter number="3" sequence="3" points="28"/>
      <quarter number="4" sequence="4" points="21"/>
    </scoring>
    <leaders>
      <points>
        <player full_name="Ryan Kelly" position="F" primary_position="PF" jersey_number="4" id="2b93904c-7655-46fe-992e-66a6501edaac">
          <statistics minutes="41:46" field_goals_made="8" field_goals_att="16" field_goals_pct="50.0" three_points_made="3" three_points_att="7" three_points_pct="42.9" two_points_made="5" two_points_att="9" two_points_pct="0.556" blocked_att="1" free_throws_made="7" free_throws_att="9" free_throws_pct="77.8" offensive_rebounds="1" defensive_rebounds="5" rebounds="6" assists="0" turnovers="2" steals="1" blocks="0" assists_turnover_ratio="0.0" personal_fouls="4" tech_fouls="0" flagrant_fouls="0" pls_min="-1" points="26"/>
        </player>
      </points>
      <rebounds>
        <player full_name="Steve Blake" position="G" primary_position="PG" jersey_number="5" id="b7ede5da-bc2f-47fe-8468-dd4b2679603c">
          <statistics minutes="39:54" field_goals_made="2" field_goals_att="7" field_goals_pct="28.6" three_points_made="2" three_points_att="7" three_points_pct="28.6" two_points_made="0" two_points_att="0" two_points_pct="0" blocked_att="0" free_throws_made="5" free_throws_att="6" free_throws_pct="83.3" offensive_rebounds="0" defensive_rebounds="10" rebounds="10" assists="15" turnovers="7" steals="3" blocks="0" assists_turnover_ratio="2.14" personal_fouls="2" tech_fouls="0" flagrant_fouls="0" pls_min="16" points="11"/>
        </player>
      </rebounds>
      <assists>
        <player full_name="Steve Blake" position="G" primary_position="PG" jersey_number="5" id="b7ede5da-bc2f-47fe-8468-dd4b2679603c">
          <statistics minutes="39:54" field_goals_made="2" field_goals_att="7" field_goals_pct="28.6" three_points_made="2" three_points_att="7" three_points_pct="28.6" two_points_made="0" two_points_att="0" two_points_pct="0" blocked_att="0" free_throws_made="5" free_throws_att="6" free_throws_pct="83.3" offensive_rebounds="0" defensive_rebounds="10" rebounds="10" assists="15" turnovers="7" steals="3" blocks="0" assists_turnover_ratio="2.14" personal_fouls="2" tech_fouls="0" flagrant_fouls="0" pls_min="16" points="11"/>
        </player>
      </assists>
    </leaders>
  </team>
</game>
<!-- Generation ended @ 2014-02-06 18:05:42 +0000 -->
