<?xml version="1.0" encoding="UTF-8"?>
<!-- Generation started @ 2014-01-04 03:54:24 +0000 -->
<game xmlns="http://feed.elasticstats.com/schema/basketball/game-v2.0.xsd" id="a8591370-53f8-46b8-961f-ece25010a000" status="closed" coverage="full" home_team="583ecb3a-fb46-11e1-82cb-f4ce4684ea4c" away_team="583ec70e-fb46-11e1-82cb-f4ce4684ea4c" scheduled="2014-01-04T01:00:00+00:00" duration="2:17" attendance="18304" lead_changes="18" times_tied="14" clock="00:00" quarter="4">
  <team name="Rockets" market="Houston" id="583ecb3a-fb46-11e1-82cb-f4ce4684ea4c" points="102">
    <scoring>
      <quarter number="1" sequence="1" points="20"/>
      <quarter number="2" sequence="2" points="28"/>
      <quarter number="3" sequence="3" points="25"/>
      <quarter number="4" sequence="4" points="29"/>
    </scoring>
    <leaders>
      <points>
        <player full_name="James Harden" position="G" primary_position="SG" jersey_number="13" id="a52b2c84-9c3d-4d6e-8a3b-10e75d11c2bc">
          <statistics minutes="44:28" field_goals_made="10" field_goals_att="19" field_goals_pct="52.6" three_points_made="5" three_points_att="10" three_points_pct="50.0" two_points_made="5" two_points_att="9" two_points_pct="0.556" blocked_att="0" free_throws_made="12" free_throws_att="12" free_throws_pct="100.0" offensive_rebounds="2" defensive_rebounds="5" rebounds="7" assists="6" turnovers="5" steals="0" blocks="0" assists_turnover_ratio="1.2" personal_fouls="2" tech_fouls="0" flagrant_fouls="0" pls_min="-2" points="37"/>
        </player>
      </points>
      <rebounds>
        <player full_name="Chandler Parsons" position="F" primary_position="SF" jersey_number="25" id="434e09b0-2da5-44f4-b406-b5a80852d71d">
          <statistics minutes="44:21" field_goals_made="6" field_goals_att="13" field_goals_pct="46.2" three_points_made="1" three_points_att="5" three_points_pct="20.0" two_points_made="5" two_points_att="8" two_points_pct="0.625" blocked_att="0" free_throws_made="4" free_throws_att="5" free_throws_pct="80.0" offensive_rebounds="1" defensive_rebounds="10" rebounds="11" assists="2" turnovers="2" steals="3" blocks="0" assists_turnover_ratio="1.0" personal_fouls="2" tech_fouls="0" flagrant_fouls="0" pls_min="-3" points="17"/>
        </player>
      </rebounds>
      <assists>
        <player full_name="James Harden" position="G" primary_position="SG" jersey_number="13" id="a52b2c84-9c3d-4d6e-8a3b-10e75d11c2bc">
          <statistics minutes="44:28" field_goals_made="10" field_goals_att="19" field_goals_pct="52.6" three_points_made="5" three_points_att="10" three_points_pct="50.0" two_points_made="5" two_points_att="9" two_points_pct="0.556" blocked_att="0" free_throws_made="12" free_throws_att="12" free_throws_pct="100.0" offensive_rebounds="2" defensive_rebounds="5" rebounds="7" assists="6" turnovers="5" steals="0" blocks="0" assists_turnover_ratio="1.2" personal_fouls="2" tech_fouls="0" flagrant_fouls="0" pls_min="-2" points="37"/>
        </player>
      </assists>
    </leaders>
  </team>
  <team name="Knicks" market="New York" id="583ec70e-fb46-11e1-82cb-f4ce4684ea4c" points="100">
    <scoring>
      <quarter number="1" sequence="1" points="24"/>
      <quarter number="2" sequence="2" points="23"/>
      <quarter number="3" sequence="3" points="34"/>
      <quarter number="4" sequence="4" points="19"/>
    </scoring>
    <leaders>
      <points>
        <player full_name="Iman Shumpert" position="G-F" primary_position="SG" jersey_number="21" id="1f9ac202-95e8-4974-9a94-ff3609ca7441">
          <statistics minutes="35:35" field_goals_made="9" field_goals_att="14" field_goals_pct="64.3" three_points_made="6" three_points_att="6" three_points_pct="100.0" two_points_made="3" two_points_att="8" two_points_pct="0.375" blocked_att="0" free_throws_made="2" free_throws_att="2" free_throws_pct="100.0" offensive_rebounds="1" defensive_rebounds="3" rebounds="4" assists="5" turnovers="0" steals="1" blocks="0" assists_turnover_ratio="0" personal_fouls="3" tech_fouls="0" flagrant_fouls="0" pls_min="10" points="26"/>
        </player>
      </points>
      <rebounds>
        <player full_name="Tyson Chandler" position="C" primary_position="C" jersey_number="6" id="3cd2d1c1-d575-45fd-b069-3f0adf57796d">
          <statistics minutes="27:17" field_goals_made="4" field_goals_att="5" field_goals_pct="80.0" three_points_made="0" three_points_att="0" three_points_pct="0.0" two_points_made="4" two_points_att="5" two_points_pct="0.8" blocked_att="1" free_throws_made="5" free_throws_att="7" free_throws_pct="71.4" offensive_rebounds="5" defensive_rebounds="6" rebounds="11" assists="0" turnovers="1" steals="1" blocks="1" assists_turnover_ratio="0.0" personal_fouls="3" tech_fouls="1" flagrant_fouls="0" points="13"/>
        </player>
      </rebounds>
      <assists>
        <player full_name="Beno Udrih" position="G" primary_position="PG" jersey_number="18" id="f77263f9-a97c-45b9-91f0-0f0da4156b9f">
          <statistics minutes="34:12" field_goals_made="5" field_goals_att="13" field_goals_pct="38.5" three_points_made="0" three_points_att="1" three_points_pct="0.0" two_points_made="5" two_points_att="12" two_points_pct="0.417" blocked_att="0" free_throws_made="0" free_throws_att="0" free_throws_pct="0.0" offensive_rebounds="1" defensive_rebounds="3" rebounds="4" assists="7" turnovers="0" steals="2" blocks="0" assists_turnover_ratio="0" personal_fouls="3" tech_fouls="0" flagrant_fouls="0" pls_min="-1" points="10"/>
        </player>
      </assists>
    </leaders>
  </team>
</game>
<!-- Generation ended @ 2014-01-04 03:54:24 +0000 -->
