<?xml version="1.0" encoding="UTF-8"?>
<!-- Generation started @ 2014-01-25 07:10:07 +0000 -->
<game xmlns="http://feed.elasticstats.com/schema/basketball/game-v2.0.xsd" id="b3909b82-f743-4857-a9c7-b031be2d0697" status="closed" coverage="full" home_team="583ec825-fb46-11e1-82cb-f4ce4684ea4c" away_team="583eca2f-fb46-11e1-82cb-f4ce4684ea4c" scheduled="2014-01-25T03:30:00+00:00" duration="2:06" attendance="19596" lead_changes="14" times_tied="16" clock="00:00" quarter="4">
  <team name="Warriors" market="Golden State" id="583ec825-fb46-11e1-82cb-f4ce4684ea4c" points="120">
    <scoring>
      <quarter number="1" sequence="1" points="36"/>
      <quarter number="2" sequence="2" points="27"/>
      <quarter number="3" sequence="3" points="35"/>
      <quarter number="4" sequence="4" points="22"/>
    </scoring>
    <leaders>
      <points>
        <player full_name="Stephen Curry" position="G" primary_position="PG" jersey_number="30" id="8ec91366-faea-4196-bbfd-b8fab7434795">
          <statistics minutes="36:53" field_goals_made="12" field_goals_att="21" field_goals_pct="57.1" three_points_made="6" three_points_att="10" three_points_pct="60.0" two_points_made="6" two_points_att="11" two_points_pct="0.545" blocked_att="0" free_throws_made="3" free_throws_att="3" free_throws_pct="100.0" offensive_rebounds="1" defensive_rebounds="2" rebounds="3" assists="15" turnovers="5" steals="1" blocks="0" assists_turnover_ratio="3.0" personal_fouls="3" tech_fouls="0" flagrant_fouls="0" pls_min="-3" points="33"/>
        </player>
      </points>
      <rebounds>
        <player full_name="Andrew Bogut" position="C" primary_position="C" jersey_number="12" id="26734851-dce6-4e5b-8291-594a7ebd6658">
          <statistics minutes="32:01" field_goals_made="4" field_goals_att="5" field_goals_pct="80.0" three_points_made="0" three_points_att="0" three_points_pct="0.0" two_points_made="4" two_points_att="5" two_points_pct="0.8" blocked_att="0" free_throws_made="0" free_throws_att="0" free_throws_pct="0.0" offensive_rebounds="3" defensive_rebounds="8" rebounds="11" assists="1" turnovers="0" steals="0" blocks="7" assists_turnover_ratio="0" personal_fouls="5" tech_fouls="0" flagrant_fouls="0" pls_min="-8" points="8"/>
        </player>
      </rebounds>
      <assists>
        <player full_name="Stephen Curry" position="G" primary_position="PG" jersey_number="30" id="8ec91366-faea-4196-bbfd-b8fab7434795">
          <statistics minutes="36:53" field_goals_made="12" field_goals_att="21" field_goals_pct="57.1" three_points_made="6" three_points_att="10" three_points_pct="60.0" two_points_made="6" two_points_att="11" two_points_pct="0.545" blocked_att="0" free_throws_made="3" free_throws_att="3" free_throws_pct="100.0" offensive_rebounds="1" defensive_rebounds="2" rebounds="3" assists="15" turnovers="5" steals="1" blocks="0" assists_turnover_ratio="3.0" personal_fouls="3" tech_fouls="0" flagrant_fouls="0" pls_min="-3" points="33"/>
        </player>
      </assists>
    </leaders>
  </team>
  <team name="Timberwolves" market="Minnesota" id="583eca2f-fb46-11e1-82cb-f4ce4684ea4c" points="121">
    <scoring>
      <quarter number="1" sequence="1" points="36"/>
      <quarter number="2" sequence="2" points="27"/>
      <quarter number="3" sequence="3" points="28"/>
      <quarter number="4" sequence="4" points="30"/>
    </scoring>
    <leaders>
      <points>
        <player full_name="Kevin Martin" position="G" primary_position="SG" jersey_number="23" id="767837db-62fa-4fc6-b118-1d56a8b23415">
          <statistics minutes="34:21" field_goals_made="10" field_goals_att="17" field_goals_pct="58.8" three_points_made="3" three_points_att="3" three_points_pct="100.0" two_points_made="7" two_points_att="14" two_points_pct="0.5" blocked_att="1" free_throws_made="3" free_throws_att="5" free_throws_pct="60.0" offensive_rebounds="1" defensive_rebounds="3" rebounds="4" assists="2" turnovers="2" steals="1" blocks="0" assists_turnover_ratio="1.0" personal_fouls="4" tech_fouls="0" flagrant_fouls="0" pls_min="7" points="26"/>
        </player>
      </points>
      <rebounds>
        <player full_name="Kevin Love" position="F-C" primary_position="PF" jersey_number="42" id="7d615ccd-db96-42a3-9a6c-7f18ea25634e">
          <statistics minutes="36:42" field_goals_made="7" field_goals_att="18" field_goals_pct="38.9" three_points_made="1" three_points_att="5" three_points_pct="20.0" two_points_made="6" two_points_att="13" two_points_pct="0.462" blocked_att="2" free_throws_made="11" free_throws_att="14" free_throws_pct="78.6" offensive_rebounds="5" defensive_rebounds="9" rebounds="14" assists="8" turnovers="2" steals="1" blocks="0" assists_turnover_ratio="4.0" personal_fouls="1" tech_fouls="0" flagrant_fouls="0" pls_min="-1" points="26"/>
        </player>
      </rebounds>
      <assists>
        <player full_name="Ricky Rubio" position="G" primary_position="PG" jersey_number="9" id="a3531f82-7374-41e7-ac71-ef5071ad2a12">
          <statistics minutes="33:26" field_goals_made="4" field_goals_att="7" field_goals_pct="57.1" three_points_made="0" three_points_att="1" three_points_pct="0.0" two_points_made="4" two_points_att="6" two_points_pct="0.667" blocked_att="1" free_throws_made="1" free_throws_att="2" free_throws_pct="50.0" offensive_rebounds="1" defensive_rebounds="0" rebounds="1" assists="12" turnovers="4" steals="4" blocks="0" assists_turnover_ratio="3.0" personal_fouls="5" tech_fouls="0" flagrant_fouls="0" pls_min="7" points="9"/>
        </player>
      </assists>
    </leaders>
  </team>
</game>
<!-- Generation ended @ 2014-01-25 07:10:08 +0000 -->
