<?xml version="1.0" encoding="UTF-8"?>
<!-- Generation started @ 2014-03-10 20:30:46 +0000 -->
<game xmlns="http://feed.elasticstats.com/schema/basketball/game-v2.0.xsd" id="da1e8419-b1e2-4f49-833a-f77e8da52a89" status="closed" coverage="full" home_team="583eccfa-fb46-11e1-82cb-f4ce4684ea4c" away_team="583ec825-fb46-11e1-82cb-f4ce4684ea4c" scheduled="2014-03-06T00:30:00+00:00" duration="2:03" attendance="18155" lead_changes="0" times_tied="0" clock="00:00" quarter="4">
  <venue id="7d69b080-91ca-53c9-9302-45c1a72c5549" name="TD Garden" capacity="17565" address="100 Legends Way" city="Boston" state="MA" zip="02114" country="USA"/>
  <team name="Celtics" market="Boston" id="583eccfa-fb46-11e1-82cb-f4ce4684ea4c" points="88">
    <scoring>
      <quarter number="1" sequence="1" points="22"/>
      <quarter number="2" sequence="2" points="18"/>
      <quarter number="3" sequence="3" points="14"/>
      <quarter number="4" sequence="4" points="34"/>
    </scoring>
    <statistics minutes="4:00:00" field_goals_made="30" field_goals_att="76" field_goals_pct="39.5" three_points_made="7" three_points_att="26" three_points_pct="26.9" two_points_made="23" two_points_att="50" two_points_pct="0.46" blocked_att="6" free_throws_made="21" free_throws_att="26" free_throws_pct="80.8" offensive_rebounds="11" defensive_rebounds="29" rebounds="40" assists="19" turnovers="22" steals="4" blocks="5" assists_turnover_ratio="0.86" personal_fouls="16" points="88" fast_break_pts="11" paint_pts="32" second_chance_pts="14" team_turnovers="0" points_off_turnovers="10" team_rebounds="12" flagrant_fouls="0" player_tech_fouls="0" team_tech_fouls="0" coach_tech_fouls="0"/>
    <players>
      <player full_name="Chris Babb" first_name="Chris" last_name="Babb" position="G-F" primary_position="SG" jersey_number="52" id="2c9b1fc5-7590-425a-a7e9-d02a7e3f8d7c" played="true" active="true">
        <statistics minutes="23:41" field_goals_made="2" field_goals_att="5" field_goals_pct="40.0" three_points_made="1" three_points_att="4" three_points_pct="25.0" two_points_made="1" two_points_att="1" two_points_pct="1.0" blocked_att="0" free_throws_made="0" free_throws_att="0" free_throws_pct="0.0" offensive_rebounds="1" defensive_rebounds="4" rebounds="5" assists="0" turnovers="0" steals="0" blocks="0" assists_turnover_ratio="0" personal_fouls="0" tech_fouls="0" flagrant_fouls="0" pls_min="4" points="5"/>
      </player>
      <player full_name="Kelly Olynyk" first_name="Kelly" last_name="Olynyk" position="C-F" primary_position="C" jersey_number="41" id="8e288d6e-50b8-404b-812b-823ae5bab61f" played="true" active="true">
        <injuries>
          <injury comment="Olnyk returned to practice Tuesday (3/4)." desc="Toe" status="Day To Day" id="3eec01af-d65f-41a6-bcf7-a1743b99ba97" start_date="2014-02-26" update_date="2014-03-04"/>
        </injuries>
        <statistics minutes="27:21" field_goals_made="6" field_goals_att="12" field_goals_pct="50.0" three_points_made="3" three_points_att="6" three_points_pct="50.0" two_points_made="3" two_points_att="6" two_points_pct="0.5" blocked_att="1" free_throws_made="4" free_throws_att="4" free_throws_pct="100.0" offensive_rebounds="2" defensive_rebounds="3" rebounds="5" assists="3" turnovers="2" steals="0" blocks="1" assists_turnover_ratio="1.5" personal_fouls="4" tech_fouls="0" flagrant_fouls="0" pls_min="2" points="19"/>
      </player>
      <player full_name="Joel Anthony" first_name="Joel" last_name="Anthony" position="C" primary_position="C" jersey_number="50" id="db276a05-67d9-45fc-a5b1-96aeea8e83df" played="true" active="true">
        <statistics minutes="3:51" field_goals_made="0" field_goals_att="1" field_goals_pct="0.0" three_points_made="0" three_points_att="0" three_points_pct="0.0" two_points_made="0" two_points_att="1" two_points_pct="0.0" blocked_att="0" free_throws_made="0" free_throws_att="0" free_throws_pct="0.0" offensive_rebounds="1" defensive_rebounds="0" rebounds="1" assists="0" turnovers="0" steals="0" blocks="0" assists_turnover_ratio="0" personal_fouls="2" tech_fouls="0" flagrant_fouls="0" pls_min="6" points="0"/>
      </player>
      <player full_name="Brandon Bass" first_name="Brandon" last_name="Bass" position="F" primary_position="PF" jersey_number="30" id="d214d3a9-9aaa-4296-bcf0-60a1769d7a70" played="true" active="true" starter="true">
        <statistics minutes="23:32" field_goals_made="4" field_goals_att="5" field_goals_pct="80.0" three_points_made="0" three_points_att="0" three_points_pct="0.0" two_points_made="4" two_points_att="5" two_points_pct="0.8" blocked_att="0" free_throws_made="3" free_throws_att="3" free_throws_pct="100.0" offensive_rebounds="3" defensive_rebounds="5" rebounds="8" assists="1" turnovers="1" steals="0" blocks="0" assists_turnover_ratio="1.0" personal_fouls="0" tech_fouls="0" flagrant_fouls="0" pls_min="-23" points="11"/>
      </player>
      <player full_name="Vitor Faverani" first_name="Vitor" last_name="Faverani" position="C" primary_position="C" jersey_number="38" id="cd73d016-9a69-4163-ae8a-14140704c68d">
        <injuries>
          <injury comment="Faverani might need knee surgery and could be done for the season." desc="Knee" status="Out Indefinitely" id="624b1ab7-396b-44d8-ba17-d699a7f9b511" start_date="2014-02-05" update_date="2014-02-28"/>
        </injuries>
        <statistics field_goals_made="0" field_goals_att="0" field_goals_pct="0.0" three_points_made="0" three_points_att="0" three_points_pct="0.0" two_points_made="0" two_points_att="0" two_points_pct="0" blocked_att="0" free_throws_made="0" free_throws_att="0" free_throws_pct="0.0" offensive_rebounds="0" defensive_rebounds="0" rebounds="0" assists="0" turnovers="0" steals="0" blocks="0" assists_turnover_ratio="0" personal_fouls="0" tech_fouls="0" flagrant_fouls="0" points="0"/>
      </player>
      <player full_name="Avery Bradley" first_name="Avery" last_name="Bradley" position="G" primary_position="PG" jersey_number="0" id="b23917d2-bb0d-49fa-a384-80d994561d0c">
        <injuries>
          <injury comment="Avery will undergo an MRI on his injured ankle Wednesday (3/5)." desc="Ankle" status="Out Indefinitely" id="7c65110e-9958-4b7f-8644-438f4a1bc0ac" start_date="2014-02-10" update_date="2014-03-04"/>
        </injuries>
        <statistics field_goals_made="0" field_goals_att="0" field_goals_pct="0.0" three_points_made="0" three_points_att="0" three_points_pct="0.0" two_points_made="0" two_points_att="0" two_points_pct="0" blocked_att="0" free_throws_made="0" free_throws_att="0" free_throws_pct="0.0" offensive_rebounds="0" defensive_rebounds="0" rebounds="0" assists="0" turnovers="0" steals="0" blocks="0" assists_turnover_ratio="0" personal_fouls="0" tech_fouls="0" flagrant_fouls="0" points="0"/>
      </player>
      <player full_name="Chris Johnson" first_name="Chris" last_name="Johnson" position="F-G" primary_position="SF" jersey_number="12" id="e3848f10-1f5a-4feb-b2ad-0b4dce9b1209" played="true" active="true">
        <statistics minutes="25:49" field_goals_made="2" field_goals_att="8" field_goals_pct="25.0" three_points_made="1" three_points_att="4" three_points_pct="25.0" two_points_made="1" two_points_att="4" two_points_pct="0.25" blocked_att="1" free_throws_made="0" free_throws_att="0" free_throws_pct="0.0" offensive_rebounds="1" defensive_rebounds="1" rebounds="2" assists="1" turnovers="1" steals="1" blocks="0" assists_turnover_ratio="1.0" personal_fouls="0" tech_fouls="0" flagrant_fouls="0" pls_min="6" points="5"/>
      </player>
      <player full_name="Gerald Wallace" first_name="Gerald" last_name="Wallace" position="F" primary_position="SF" jersey_number="45" id="7ac35d55-3283-48dc-9609-ed342b3eda56" active="true">
        <injuries>
          <injury comment="Wallace underwent season ending surgery to repair his ankle and his torn left meniscus on Tuesday (3/4)." desc="Knee" status="Out For Season" id="1f813934-1a4c-46c4-ad94-949912518d1f" start_date="2014-02-28" update_date="2014-03-04"/>
        </injuries>
        <statistics field_goals_made="0" field_goals_att="0" field_goals_pct="0.0" three_points_made="0" three_points_att="0" three_points_pct="0.0" two_points_made="0" two_points_att="0" two_points_pct="0" blocked_att="0" free_throws_made="0" free_throws_att="0" free_throws_pct="0.0" offensive_rebounds="0" defensive_rebounds="0" rebounds="0" assists="0" turnovers="0" steals="0" blocks="0" assists_turnover_ratio="0" personal_fouls="0" tech_fouls="0" flagrant_fouls="0" points="0"/>
      </player>
      <player full_name="Jeff Green" first_name="Jeff" last_name="Green" position="G-F" primary_position="SF" jersey_number="8" id="b9155864-4192-4ad7-8652-57a0844c87b3" played="true" active="true" starter="true">
        <statistics minutes="24:19" field_goals_made="2" field_goals_att="7" field_goals_pct="28.6" three_points_made="0" three_points_att="1" three_points_pct="0.0" two_points_made="2" two_points_att="6" two_points_pct="0.333" blocked_att="1" free_throws_made="0" free_throws_att="0" free_throws_pct="0.0" offensive_rebounds="1" defensive_rebounds="2" rebounds="3" assists="2" turnovers="2" steals="0" blocks="2" assists_turnover_ratio="1.0" personal_fouls="1" tech_fouls="0" flagrant_fouls="0" pls_min="-24" points="4"/>
      </player>
      <player full_name="Phil Pressey" first_name="Phil" last_name="Pressey" position="G" primary_position="PG" jersey_number="26" id="e5b54fa6-88e0-4702-9677-282f204a43e1" played="true" active="true">
        <statistics minutes="10:49" field_goals_made="3" field_goals_att="4" field_goals_pct="75.0" three_points_made="1" three_points_att="2" three_points_pct="50.0" two_points_made="2" two_points_att="2" two_points_pct="1.0" blocked_att="0" free_throws_made="0" free_throws_att="0" free_throws_pct="0.0" offensive_rebounds="0" defensive_rebounds="1" rebounds="1" assists="5" turnovers="2" steals="1" blocks="0" assists_turnover_ratio="2.5" personal_fouls="0" tech_fouls="0" flagrant_fouls="0" pls_min="2" points="7"/>
      </player>
      <player full_name="Jared Sullinger" first_name="Jared" last_name="Sullinger" position="C-F" primary_position="C" jersey_number="7" id="cdda9628-563e-4d3e-a660-d9665aaa94a3" played="true" active="true">
        <statistics minutes="25:31" field_goals_made="1" field_goals_att="7" field_goals_pct="14.3" three_points_made="0" three_points_att="3" three_points_pct="0.0" two_points_made="1" two_points_att="4" two_points_pct="0.25" blocked_att="0" free_throws_made="9" free_throws_att="10" free_throws_pct="90.0" offensive_rebounds="1" defensive_rebounds="3" rebounds="4" assists="0" turnovers="3" steals="1" blocks="0" assists_turnover_ratio="0.0" personal_fouls="4" tech_fouls="0" flagrant_fouls="0" pls_min="-13" points="11"/>
      </player>
      <player full_name="Kris Humphries" first_name="Kris" last_name="Humphries" position="C-F" primary_position="C" jersey_number="43" id="1a072572-763d-4839-b920-82b48d8e296a" played="true" active="true" starter="true">
        <statistics minutes="15:45" field_goals_made="1" field_goals_att="5" field_goals_pct="20.0" three_points_made="0" three_points_att="0" three_points_pct="0.0" two_points_made="1" two_points_att="5" two_points_pct="0.2" blocked_att="1" free_throws_made="0" free_throws_att="0" free_throws_pct="0.0" offensive_rebounds="0" defensive_rebounds="3" rebounds="3" assists="0" turnovers="3" steals="0" blocks="1" assists_turnover_ratio="0.0" personal_fouls="0" tech_fouls="0" flagrant_fouls="0" pls_min="-12" points="2"/>
      </player>
      <player full_name="Rajon Rondo" first_name="Rajon" last_name="Rondo" position="G" primary_position="PG" jersey_number="9" id="977b67b1-4665-4f97-ba3b-7d7778efecdb" played="true" active="true" starter="true">
        <statistics minutes="37:11" field_goals_made="6" field_goals_att="14" field_goals_pct="42.9" three_points_made="1" three_points_att="5" three_points_pct="20.0" two_points_made="5" two_points_att="9" two_points_pct="0.556" blocked_att="1" free_throws_made="1" free_throws_att="4" free_throws_pct="25.0" offensive_rebounds="0" defensive_rebounds="5" rebounds="5" assists="7" turnovers="7" steals="1" blocks="1" assists_turnover_ratio="1.0" personal_fouls="3" tech_fouls="0" flagrant_fouls="0" pls_min="-22" points="14"/>
      </player>
      <player full_name="Keith Bogans" first_name="Keith" last_name="Bogans" position="G-F" primary_position="SG" jersey_number="4" id="ded880d5-f1a9-4cfa-a16e-6604e0a16529">
        <injuries>
          <injury comment="Excused from team activities indefinitely." desc="Personal" status="Out" id="433c5be8-6d97-447e-a77c-b622f0bda8e5" start_date="2014-01-14" update_date="2014-01-14"/>
        </injuries>
        <statistics field_goals_made="0" field_goals_att="0" field_goals_pct="0.0" three_points_made="0" three_points_att="0" three_points_pct="0.0" two_points_made="0" two_points_att="0" two_points_pct="0" blocked_att="0" free_throws_made="0" free_throws_att="0" free_throws_pct="0.0" offensive_rebounds="0" defensive_rebounds="0" rebounds="0" assists="0" turnovers="0" steals="0" blocks="0" assists_turnover_ratio="0" personal_fouls="0" tech_fouls="0" flagrant_fouls="0" points="0"/>
      </player>
      <player full_name="Jerryd Bayless" first_name="Jerryd" last_name="Bayless" position="G" primary_position="PG" jersey_number="11" id="f444ee53-e3b3-4899-923e-a27369ce7e59" played="true" active="true" starter="true">
        <statistics minutes="22:11" field_goals_made="3" field_goals_att="8" field_goals_pct="37.5" three_points_made="0" three_points_att="1" three_points_pct="0.0" two_points_made="3" two_points_att="7" two_points_pct="0.429" blocked_att="1" free_throws_made="4" free_throws_att="5" free_throws_pct="80.0" offensive_rebounds="1" defensive_rebounds="2" rebounds="3" assists="0" turnovers="1" steals="0" blocks="0" assists_turnover_ratio="0.0" personal_fouls="2" tech_fouls="0" flagrant_fouls="0" pls_min="-26" points="10"/>
      </player>
    </players>
  </team>
  <team name="Warriors" market="Golden State" id="583ec825-fb46-11e1-82cb-f4ce4684ea4c" points="108">
    <scoring>
      <quarter number="1" sequence="1" points="30"/>
      <quarter number="2" sequence="2" points="31"/>
      <quarter number="3" sequence="3" points="23"/>
      <quarter number="4" sequence="4" points="24"/>
    </scoring>
    <statistics minutes="4:00:00" field_goals_made="46" field_goals_att="98" field_goals_pct="46.9" three_points_made="5" three_points_att="28" three_points_pct="17.9" two_points_made="41" two_points_att="70" two_points_pct="0.586" blocked_att="5" free_throws_made="11" free_throws_att="12" free_throws_pct="91.7" offensive_rebounds="15" defensive_rebounds="30" rebounds="45" assists="28" turnovers="11" steals="13" blocks="6" assists_turnover_ratio="2.55" personal_fouls="24" points="108" fast_break_pts="25" paint_pts="58" second_chance_pts="18" team_turnovers="0" points_off_turnovers="24" team_rebounds="7" flagrant_fouls="0" player_tech_fouls="0" team_tech_fouls="0" coach_tech_fouls="0"/>
    <players>
      <player full_name="David Lee" first_name="David" last_name="Lee" position="F" primary_position="PF" jersey_number="10" id="9a48ac5c-430e-4306-b393-bd366e922334" played="true" active="true" starter="true">
        <statistics minutes="24:44" field_goals_made="9" field_goals_att="17" field_goals_pct="52.9" three_points_made="0" three_points_att="0" three_points_pct="0.0" two_points_made="9" two_points_att="17" two_points_pct="0.529" blocked_att="1" free_throws_made="0" free_throws_att="0" free_throws_pct="0.0" offensive_rebounds="5" defensive_rebounds="5" rebounds="10" assists="3" turnovers="1" steals="2" blocks="0" assists_turnover_ratio="3.0" personal_fouls="3" tech_fouls="0" flagrant_fouls="0" pls_min="27" points="18"/>
      </player>
      <player full_name="Draymond Green" first_name="Draymond" last_name="Green" position="F" primary_position="SF" jersey_number="23" id="5e5099d1-4a58-43f2-8d03-f2ae5dd49337" played="true" active="true">
        <statistics minutes="23:16" field_goals_made="3" field_goals_att="7" field_goals_pct="42.9" three_points_made="0" three_points_att="2" three_points_pct="0.0" two_points_made="3" two_points_att="5" two_points_pct="0.6" blocked_att="0" free_throws_made="1" free_throws_att="2" free_throws_pct="50.0" offensive_rebounds="1" defensive_rebounds="4" rebounds="5" assists="4" turnovers="3" steals="2" blocks="1" assists_turnover_ratio="1.33" personal_fouls="4" tech_fouls="0" flagrant_fouls="0" pls_min="-7" points="7"/>
      </player>
      <player full_name="Jordan Crawford" first_name="Jordan" last_name="Crawford" position="G" primary_position="SG" jersey_number="55" id="264a1d66-7f41-465a-b64c-c0f20ab31ad3" played="true" active="true">
        <statistics minutes="19:26" field_goals_made="7" field_goals_att="12" field_goals_pct="58.3" three_points_made="1" three_points_att="5" three_points_pct="20.0" two_points_made="6" two_points_att="7" two_points_pct="0.857" blocked_att="0" free_throws_made="0" free_throws_att="0" free_throws_pct="0.0" offensive_rebounds="1" defensive_rebounds="0" rebounds="1" assists="1" turnovers="2" steals="0" blocks="0" assists_turnover_ratio="0.5" personal_fouls="2" tech_fouls="0" flagrant_fouls="0" pls_min="-10" points="15"/>
      </player>
      <player full_name="Marreese Speights" first_name="Marreese" last_name="Speights" position="F-C" primary_position="PF" jersey_number="5" id="e4bd8c65-a40b-42e3-8327-6913045bf008" played="true" active="true">
        <statistics minutes="12:00" field_goals_made="1" field_goals_att="4" field_goals_pct="25.0" three_points_made="0" three_points_att="1" three_points_pct="0.0" two_points_made="1" two_points_att="3" two_points_pct="0.333" blocked_att="0" free_throws_made="5" free_throws_att="5" free_throws_pct="100.0" offensive_rebounds="2" defensive_rebounds="3" rebounds="5" assists="1" turnovers="3" steals="0" blocks="0" assists_turnover_ratio="0.33" personal_fouls="1" tech_fouls="0" flagrant_fouls="0" pls_min="-10" points="7"/>
      </player>
      <player full_name="Andrew Bogut" first_name="Andrew" last_name="Bogut" position="C" primary_position="C" jersey_number="12" id="26734851-dce6-4e5b-8291-594a7ebd6658" played="true" active="true" starter="true">
        <statistics minutes="23:46" field_goals_made="2" field_goals_att="4" field_goals_pct="50.0" three_points_made="0" three_points_att="0" three_points_pct="0.0" two_points_made="2" two_points_att="4" two_points_pct="0.5" blocked_att="1" free_throws_made="0" free_throws_att="0" free_throws_pct="0.0" offensive_rebounds="4" defensive_rebounds="4" rebounds="8" assists="4" turnovers="1" steals="1" blocks="4" assists_turnover_ratio="4.0" personal_fouls="4" tech_fouls="0" flagrant_fouls="0" pls_min="26" points="4"/>
      </player>
      <player full_name="Harrison Barnes" first_name="Harrison" last_name="Barnes" position="F" primary_position="SF" jersey_number="40" id="ce8d0944-b277-499e-9701-02a5f1828615" played="true" active="true">
        <statistics minutes="25:04" field_goals_made="1" field_goals_att="8" field_goals_pct="12.5" three_points_made="1" three_points_att="3" three_points_pct="33.3" two_points_made="0" two_points_att="5" two_points_pct="0.0" blocked_att="0" free_throws_made="0" free_throws_att="0" free_throws_pct="0.0" offensive_rebounds="1" defensive_rebounds="1" rebounds="2" assists="0" turnovers="0" steals="2" blocks="0" assists_turnover_ratio="0" personal_fouls="2" tech_fouls="0" flagrant_fouls="0" pls_min="-6" points="3"/>
      </player>
      <player full_name="Festus Ezeli" first_name="Festus" last_name="Ezeli" position="C" primary_position="C" jersey_number="31" id="17973022-bb81-427f-905e-86d3d3d9b51f">
        <injuries>
          <injury comment="Ezeli could return by April." desc="Knee Surgery" status="Out" id="d1b5fdd7-c725-4128-8894-a8d1b4ae2bf1" start_date="2013-06-13" update_date="2014-02-20"/>
        </injuries>
        <statistics field_goals_made="0" field_goals_att="0" field_goals_pct="0.0" three_points_made="0" three_points_att="0" three_points_pct="0.0" two_points_made="0" two_points_att="0" two_points_pct="0" blocked_att="0" free_throws_made="0" free_throws_att="0" free_throws_pct="0.0" offensive_rebounds="0" defensive_rebounds="0" rebounds="0" assists="0" turnovers="0" steals="0" blocks="0" assists_turnover_ratio="0" personal_fouls="0" tech_fouls="0" flagrant_fouls="0" points="0"/>
      </player>
      <player full_name="Nemanja Nedovic" first_name="Nemanja" last_name="Nedovic" position="G" primary_position="PG" jersey_number="8" id="30fd3dbf-2746-4d68-a573-7c68a0d12620">
        <injuries>
          <injury comment="Is expected to practice Tuesday. " desc="Hamstring" status="Out" id="6a60304d-d447-43de-99d5-42a7cdf4464f" start_date="2014-01-14" update_date="2014-02-24"/>
        </injuries>
        <statistics field_goals_made="0" field_goals_att="0" field_goals_pct="0.0" three_points_made="0" three_points_att="0" three_points_pct="0.0" two_points_made="0" two_points_att="0" two_points_pct="0" blocked_att="0" free_throws_made="0" free_throws_att="0" free_throws_pct="0.0" offensive_rebounds="0" defensive_rebounds="0" rebounds="0" assists="0" turnovers="0" steals="0" blocks="0" assists_turnover_ratio="0" personal_fouls="0" tech_fouls="0" flagrant_fouls="0" points="0"/>
      </player>
      <player full_name="Steve Blake" first_name="Steve" last_name="Blake" position="G" primary_position="PG" jersey_number="25" id="b7ede5da-bc2f-47fe-8468-dd4b2679603c" played="true" active="true">
        <statistics minutes="27:01" field_goals_made="2" field_goals_att="6" field_goals_pct="33.3" three_points_made="0" three_points_att="4" three_points_pct="0.0" two_points_made="2" two_points_att="2" two_points_pct="1.0" blocked_att="0" free_throws_made="0" free_throws_att="0" free_throws_pct="0.0" offensive_rebounds="0" defensive_rebounds="2" rebounds="2" assists="6" turnovers="0" steals="0" blocks="0" assists_turnover_ratio="0" personal_fouls="1" tech_fouls="0" flagrant_fouls="0" pls_min="-6" points="4"/>
      </player>
      <player full_name="Ognjen Kuzmic" first_name="Ognjen" last_name="Kuzmic" position="C" primary_position="C" jersey_number="1" id="43a67926-b4f3-43ef-af64-11b8ef0819fc">
        <statistics field_goals_made="0" field_goals_att="0" field_goals_pct="0.0" three_points_made="0" three_points_att="0" three_points_pct="0.0" two_points_made="0" two_points_att="0" two_points_pct="0" blocked_att="0" free_throws_made="0" free_throws_att="0" free_throws_pct="0.0" offensive_rebounds="0" defensive_rebounds="0" rebounds="0" assists="0" turnovers="0" steals="0" blocks="0" assists_turnover_ratio="0" personal_fouls="0" tech_fouls="0" flagrant_fouls="0" points="0"/>
      </player>
      <player full_name="Klay Thompson" first_name="Klay" last_name="Thompson" position="G" primary_position="SG" jersey_number="11" id="4e152a06-673e-4701-b115-aa7e2cd00d2d" played="true" active="true" starter="true">
        <statistics minutes="27:46" field_goals_made="7" field_goals_att="15" field_goals_pct="46.7" three_points_made="1" three_points_att="8" three_points_pct="12.5" two_points_made="6" two_points_att="7" two_points_pct="0.857" blocked_att="0" free_throws_made="3" free_throws_att="3" free_throws_pct="100.0" offensive_rebounds="0" defensive_rebounds="1" rebounds="1" assists="4" turnovers="0" steals="3" blocks="0" assists_turnover_ratio="0" personal_fouls="1" tech_fouls="0" flagrant_fouls="0" pls_min="26" points="18"/>
      </player>
      <player full_name="Jermaine O'Neal" first_name="Jermaine" last_name="O'Neal" position="C-F" primary_position="C" jersey_number="7" id="60bb6586-4287-4893-9688-6a109e8b03b0" played="true" active="true">
        <statistics minutes="12:10" field_goals_made="3" field_goals_att="6" field_goals_pct="50.0" three_points_made="0" three_points_att="0" three_points_pct="0.0" two_points_made="3" two_points_att="6" two_points_pct="0.5" blocked_att="1" free_throws_made="1" free_throws_att="1" free_throws_pct="100.0" offensive_rebounds="0" defensive_rebounds="4" rebounds="4" assists="0" turnovers="0" steals="1" blocks="1" assists_turnover_ratio="0" personal_fouls="1" tech_fouls="0" flagrant_fouls="0" pls_min="6" points="7"/>
      </player>
      <player full_name="Stephen Curry" first_name="Stephen" last_name="Curry" position="G" primary_position="PG" jersey_number="30" id="8ec91366-faea-4196-bbfd-b8fab7434795" played="true" active="true" starter="true">
        <statistics minutes="21:51" field_goals_made="6" field_goals_att="10" field_goals_pct="60.0" three_points_made="1" three_points_att="4" three_points_pct="25.0" two_points_made="5" two_points_att="6" two_points_pct="0.833" blocked_att="1" free_throws_made="1" free_throws_att="1" free_throws_pct="100.0" offensive_rebounds="0" defensive_rebounds="3" rebounds="3" assists="4" turnovers="0" steals="1" blocks="0" assists_turnover_ratio="0" personal_fouls="3" tech_fouls="0" flagrant_fouls="0" pls_min="28" points="14"/>
      </player>
      <player full_name="Andre Iguodala" first_name="Andre" last_name="Iguodala" position="F-G" primary_position="SF" jersey_number="9" id="9fdcd102-1c82-4e32-b366-c93139352c75" played="true" active="true" starter="true">
        <statistics minutes="22:56" field_goals_made="5" field_goals_att="9" field_goals_pct="55.6" three_points_made="1" three_points_att="1" three_points_pct="100.0" two_points_made="4" two_points_att="8" two_points_pct="0.5" blocked_att="1" free_throws_made="0" free_throws_att="0" free_throws_pct="0.0" offensive_rebounds="1" defensive_rebounds="3" rebounds="4" assists="1" turnovers="1" steals="1" blocks="0" assists_turnover_ratio="1.0" personal_fouls="2" tech_fouls="0" flagrant_fouls="0" pls_min="26" points="11"/>
      </player>
    </players>
  </team>
  <officials>
    <official full_name="Derrick Collins" first_name="Derrick" last_name="Collins" number="11" assignment="Official" experience="13" id="36e5f442-9eed-4b23-ab9b-0e498f10eb03"/>
    <official full_name="Eric Dalen" first_name="Eric" last_name="Dalen" number="75" assignment="Official" experience="6" id="812efbc8-659c-4d4b-af06-020aa611a692"/>
    <official full_name="Rodney Mott" first_name="Rodney" last_name="Mott" number="71" assignment="Head Official" experience="17" id="4362601e-767f-4b28-8b1a-9eb6606f2e36"/>
  </officials>
</game>
<!-- Generation ended @ 2014-03-10 20:30:48 +0000 -->
